baseband_tasks/__init__.py
baseband_tasks/_astropy_init.py
baseband_tasks/base.py
baseband_tasks/channelize.py
baseband_tasks/combining.py
baseband_tasks/conftest.py
baseband_tasks/conversion.py
baseband_tasks/convolution.py
baseband_tasks/dispersion.py
baseband_tasks/dm.py
baseband_tasks/functions.py
baseband_tasks/generators.py
baseband_tasks/integration.py
baseband_tasks/sampling.py
baseband_tasks/shaping.py
baseband_tasks/version.py
baseband_tasks/data/PsrfitsDocumentation.html
baseband_tasks/data/README.rst
baseband_tasks/data/__init__.py
baseband_tasks/fourier/__init__.py
baseband_tasks/fourier/base.py
baseband_tasks/fourier/numpy.py
baseband_tasks/fourier/pyfftw.py
baseband_tasks/fourier/tests/__init__.py
baseband_tasks/fourier/tests/test_fourier.py
baseband_tasks/io/__init__.py
baseband_tasks/io/hdf5/__init__.py
baseband_tasks/io/hdf5/base.py
baseband_tasks/io/hdf5/frame.py
baseband_tasks/io/hdf5/header.py
baseband_tasks/io/hdf5/payload.py
baseband_tasks/io/hdf5/tests/__init__.py
baseband_tasks/io/hdf5/tests/test_hdf5.py
baseband_tasks/io/psrfits/__init__.py
baseband_tasks/io/psrfits/core.py
baseband_tasks/io/psrfits/hdu.py
baseband_tasks/io/psrfits/psrfits_htm_parser.py
baseband_tasks/io/psrfits/tests/__init__.py
baseband_tasks/io/psrfits/tests/test_psrfits_read.py
baseband_tasks/io/psrfits/tests/test_psrfits_setter.py
baseband_tasks/io/psrfits/tests/test_psrfits_write.py
baseband_tasks/io/psrfits/tests/data/B1855+09.430.PUPPI.11y.x.sum.sm
baseband_tasks/io/psrfits/tests/data/B1855_nano.npz
baseband_tasks/phases/__init__.py
baseband_tasks/phases/core.py
baseband_tasks/phases/phase.py
baseband_tasks/phases/pint_toas.py
baseband_tasks/phases/predictor.py
baseband_tasks/tests/__init__.py
baseband_tasks/tests/common.py
baseband_tasks/tests/test_base.py
baseband_tasks/tests/test_channelize.py
baseband_tasks/tests/test_combining.py
baseband_tasks/tests/test_conversion.py
baseband_tasks/tests/test_convolution.py
baseband_tasks/tests/test_dispersion.py
baseband_tasks-0.2.dist-info/LICENSE
baseband_tasks-0.2.dist-info/METADATA
baseband_tasks-0.2.dist-info/WHEEL
baseband_tasks-0.2.dist-info/entry_points.txt
baseband_tasks-0.2.dist-info/top_level.txt
baseband_tasks-0.2.dist-info/RECORD
