Metadata-Version: 2.1
Name: baseband-tasks
Version: 0.2
Summary: A package for radio baseband data reduction and analysis
Home-page: https://baseband-tasks.readthedocs.io
Author: Marten H. van Kerkwijk, Jing Luo, Chenchong Zhu
Author-email: mhvk@astro.utoronto.ca
License: GNU GPL v3+
Project-URL: Documentation, https://baseband.readthedocs.io/projects/baseband-tasks
Platform: UNKNOWN
Provides: baseband_tasks
Requires-Python: >=3.7
Requires-Dist: baseband (>=4.0)
Provides-Extra: all
Requires-Dist: h5py ; extra == 'all'
Requires-Dist: pint-pulsar ; extra == 'all'
Requires-Dist: pyfftw ; extra == 'all'
Requires-Dist: pyyaml ; extra == 'all'
Provides-Extra: cov
Requires-Dist: pytest-cov ; extra == 'cov'
Provides-Extra: docs
Requires-Dist: h5py ; extra == 'docs'
Requires-Dist: pyfftw ; extra == 'docs'
Requires-Dist: pyyaml ; extra == 'docs'
Requires-Dist: sphinx-astropy ; extra == 'docs'
Provides-Extra: io
Requires-Dist: h5py ; extra == 'io'
Requires-Dist: pyyaml ; extra == 'io'
Provides-Extra: test
Requires-Dist: pytest-astropy-header ; extra == 'test'
Requires-Dist: pytest-doctestplus ; extra == 'test'
Requires-Dist: importlib-metadata ; (python_version < "3.8") and extra == 'test'
